{"dao1":{"progress":[["1_gamestart",29],["2_library",6],["3_ee2",3],["4_ee2",4],["5_art",4],["6_art2",4],["6wrong",2],["7_bellstory",8],["8_bell1",1],["9_bell2",2]],"UI":{"mode":"answer","QR":false,"itemMenu":false,"history":false,"itemList":[{"title":"\u59b9\u59b9\u7684\u65e5\u8a18-1","key":"diary1"},{"title":"\u59b9\u59b9\u7684\u65e5\u8a18-2","key":"diary2"},{"title":"\u6cb3\u5317\u99ac\u9234\u85af\u738b\u7559\u4e0b\u7684\u4fe1","key":"bell"}],"currentItem":null}},"dao2":{"progress":[["1_gamestart",29],["2_library",6],["3_ee2",3],["4_ee2",4],["5_art",4],["6_art2",4],["7_bellstory",8],["8_bell1",1],["9_bell2",2],["9wrong",2],["10_soclib1",2]],"UI":{"mode":"next","QR":false,"itemMenu":false,"history":true,"itemList":[{"title":"\u59b9\u59b9\u7684\u65e5\u8a18-1","key":"diary1"},{"title":"\u59b9\u59b9\u7684\u65e5\u8a18-2","key":"diary2"},{"title":"\u6cb3\u5317\u99ac\u9234\u85af\u738b\u7559\u4e0b\u7684\u4fe1","key":"bell"}],"currentItem":null}},"dao3":{"progress":[["1_gamestart",1]],"UI":{"mode":"next","QR":false,"itemMenu":false,"history":false,"itemList":[],"currentItem":null}},"dao4":{"progress":[["1_gamestart",1]],"UI":{"mode":"next","QR":false,"itemMenu":false,"history":false,"itemList":[],"currentItem":null}},"dao5":{"progress":[["1_gamestart",29],["2_library",6],["3_ee2",3],["4_ee2",4],["5_art",4],["6_art2",4],["7_bellstory",8],["8_bell1",1],["9_bell2",2],["9wrong",2],["9wrong",2],["9wrong",2],["9wrong",2],["9wrong",2]],"UI":{"mode":"answer","QR":false,"itemMenu":false,"history":false,"itemList":[{"title":"\u59b9\u59b9\u7684\u65e5\u8a18-1","key":"diary1"},{"title":"\u59b9\u59b9\u7684\u65e5\u8a18-2","key":"diary2"},{"title":"\u6cb3\u5317\u99ac\u9234\u85af\u738b\u7559\u4e0b\u7684\u4fe1","key":"bell"}],"currentItem":null}},"dao6":{"progress":[["1_gamestart",1]],"UI":{"mode":"next","QR":false,"itemMenu":false,"history":false,"itemList":[],"currentItem":null}},"dao7":{"progress":[["1_gamestart",29],["2_library",6],["3_ee2",3],["4_ee2",4],["5_art",4],["6_art2",4]],"UI":{"mode":"answer","QR":false,"itemMenu":false,"history":false,"itemList":[{"title":"\u59b9\u59b9\u7684\u65e5\u8a18-1","key":"diary1"},{"title":"\u59b9\u59b9\u7684\u65e5\u8a18-2","key":"diary2"}],"currentItem":null}},"dao8":{"progress":[["1_gamestart",29],["2_library",6],["3_ee2",3],["4_ee2",4]],"UI":{"mode":"answer","QR":false,"itemMenu":false,"history":false,"itemList":[{"title":"\u59b9\u59b9\u7684\u65e5\u8a18-1","key":"diary1"}],"currentItem":null}},"dao9":{"progress":[["1_gamestart",1]],"UI":{"mode":"next","QR":false,"itemMenu":false,"history":false,"itemList":[],"currentItem":null}},"dao10":{"progress":[["1_gamestart",1]],"UI":{"mode":"next","QR":false,"itemMenu":false,"history":false,"itemList":[],"currentItem":null}},"dao11":{"progress":[["1_gamestart",1]],"UI":{"mode":"next","QR":false,"itemMenu":false,"history":false,"itemList":[],"currentItem":null}},"dao12":{"progress":[["1_gamestart",1]],"UI":{"mode":"next","QR":false,"itemMenu":false,"history":false,"itemList":[],"currentItem":null}},"dao13":{"progress":[["1_gamestart",1]],"UI":{"mode":"next","QR":false,"itemMenu":false,"history":false,"itemList":[],"currentItem":null}},"dao14":{"progress":[["1_gamestart",29],["2_library",6],["3_ee2",3],["4_ee2",4],["5_art",4],["6_art2",4],["7_bellstory",8],["8_bell1",1],["9_bell2",2],["9wrong",2],["9wrong",2],["9wrong",2]],"UI":{"mode":"answer","QR":false,"itemMenu":false,"history":false,"itemList":[{"title":"\u59b9\u59b9\u7684\u65e5\u8a18-1","key":"diary1"},{"title":"\u59b9\u59b9\u7684\u65e5\u8a18-2","key":"diary2"},{"title":"\u6cb3\u5317\u99ac\u9234\u85af\u738b\u7559\u4e0b\u7684\u4fe1","key":"bell"}],"currentItem":null}},"dao15":{"progress":[["1_gamestart",1]],"UI":{"mode":"next","QR":false,"itemMenu":false,"history":false,"itemList":[],"currentItem":null}}}